moonglaive/__init__.py
moonglaive/__main__.py
moonglaive/main.py
src/__init__.py
src/main.py
moonglaive-0.0.1.dist-info/LICENSE
moonglaive-0.0.1.dist-info/METADATA
moonglaive-0.0.1.dist-info/WHEEL
moonglaive-0.0.1.dist-info/top_level.txt
moonglaive-0.0.1.dist-info/RECORD
