Metadata-Version: 2.1
Name: moonglaive
Version: 0.0.1
Summary: Three-bladed weapon of the night elf Sentinels
Home-page: https://github.com/MalfurionWhitehat/moonglaive
Author: MalfurionWhitehat
Author-email: MalfurionWhitehat@proton.me
License: MIT
Platform: UNKNOWN
Classifier: Development Status :: 1 - Planning
Classifier: Intended Audience :: Science/Research
Classifier: License :: OSI Approved :: BSD License
Classifier: Operating System :: POSIX :: Linux
Classifier: Programming Language :: Python :: 2
Classifier: Programming Language :: Python :: 2.7
Classifier: Programming Language :: Python :: 3
Classifier: Programming Language :: Python :: 3.4
Classifier: Programming Language :: Python :: 3.5
Requires-Dist: typing
Requires-Dist: datetime
Requires-Dist: python-dateutil
Requires-Dist: python-Levenshtein
Requires-Dist: fuzzywuzzy
Requires-Dist: requests
Requires-Dist: argparse
Requires-Dist: tabulate
